zibal/__init__.py
zibal/zibal.py
zibal-1.1.0.dist-info/LICENSE.txt
zibal-1.1.0.dist-info/METADATA
zibal-1.1.0.dist-info/WHEEL
zibal-1.1.0.dist-info/top_level.txt
zibal-1.1.0.dist-info/RECORD
