Metadata-Version: 2.1
Name: zibal
Version: 1.1.0
Summary: Zibal payment gateway
Home-page: https://docs.zibal.ir/
Author: Yahya Kangi
Author-email: yhy.kng@gmail.com
License: MIT
Download-URL: https://pypi.org/project/zibal/
Keywords: Zibal,Payment,زیبال,درگاه پرداخت,درگاه زیبال
Platform: UNKNOWN
Requires-Dist: requests
